credsmash/VERSION
credsmash/__init__.py
credsmash/cli.py
credsmash/cli_dynamodb.py
credsmash/dynamodb_storage_service.py
credsmash/kms_key_service.py
credsmash/templates.py
credsmash/util.py
credsmash/api/__init__.py
credsmash/api/delete.py
credsmash/api/get.py
credsmash/api/list.py
credsmash/api/prune.py
credsmash/api/put.py
credsmash/crypto/__init__.py
credsmash/crypto/aes_ctr.py
credsmash/crypto/aes_gcm.py
credsmash-3.0.2.dist-info/LICENSE
credsmash-3.0.2.dist-info/METADATA
credsmash-3.0.2.dist-info/WHEEL
credsmash-3.0.2.dist-info/entry_points.txt
credsmash-3.0.2.dist-info/top_level.txt
credsmash-3.0.2.dist-info/RECORD
