Metadata-Version: 2.1
Name: credsmash
Version: 3.0.2
Summary: A utility for managing secrets in the cloud using AWS KMS and DynamoDB
Home-page: https://github.com/3stack-software/credsmash
Maintainer: Nathan Muir
Maintainer-email: ndmuir@gmail.com
License: Apache2
Classifier: Intended Audience :: Developers
Classifier: Intended Audience :: System Administrators
Classifier: License :: OSI Approved :: Apache Software License
Classifier: Programming Language :: Python
Classifier: Programming Language :: Python :: 3
Classifier: Programming Language :: Python :: 3.8
Classifier: Programming Language :: Python :: 3.9
Classifier: Programming Language :: Python :: 3.10
Classifier: Programming Language :: Python :: 3.11
Classifier: Programming Language :: Python :: 3.12
Requires-Python: >=3.8
License-File: LICENSE
Requires-Dist: cryptography
Requires-Dist: boto3
Requires-Dist: click
Requires-Dist: six
Requires-Dist: importlib-resources >=5.12
Requires-Dist: importlib-metadata >=6.5
Provides-Extra: dev
Requires-Dist: PyYAML ; extra == 'dev'
Requires-Dist: jinja2 ; extra == 'dev'
Requires-Dist: pytest ; extra == 'dev'
Provides-Extra: documentation
Provides-Extra: templates
Requires-Dist: jinja2 ; extra == 'templates'
Provides-Extra: yaml
Requires-Dist: PyYAML ; extra == 'yaml'
